latex_resume_mcp/__init__.py
latex_resume_mcp/server.py
latex_resume_mcp-0.1.0.dist-info/METADATA
latex_resume_mcp-0.1.0.dist-info/WHEEL
latex_resume_mcp-0.1.0.dist-info/entry_points.txt
latex_resume_mcp-0.1.0.dist-info/licenses/LICENSE
latex_resume_mcp-0.1.0.dist-info/RECORD
