Metadata-Version: 2.4
Name: latex-resume-mcp
Version: 0.1.0
Summary: MCP server for creating, editing, and compiling LaTeX resumes
Project-URL: Homepage, https://github.com/dannywillowliu-uchi/resume_mcp
Project-URL: Repository, https://github.com/dannywillowliu-uchi/resume_mcp
Project-URL: Issues, https://github.com/dannywillowliu-uchi/resume_mcp/issues
Author: Danny Liu
License-Expression: MIT
License-File: LICENSE
Keywords: ai,claude,cv,latex,mcp,resume
Classifier: Development Status :: 4 - Beta
Classifier: Intended Audience :: Developers
Classifier: License :: OSI Approved :: MIT License
Classifier: Programming Language :: Python :: 3
Classifier: Programming Language :: Python :: 3.10
Classifier: Programming Language :: Python :: 3.11
Classifier: Programming Language :: Python :: 3.12
Requires-Python: >=3.10
Requires-Dist: mcp>=1.0.0
